rail_django_graphql/__init__.py
rail_django_graphql/apps.py
rail_django_graphql/conf.py
rail_django_graphql/decorators.py
rail_django_graphql/defaults.py
rail_django_graphql/health_urls.py
rail_django_graphql/schema.py
rail_django_graphql/security_config.py
rail_django_graphql/settings.py
rail_django_graphql/urls.py
rail_django_graphql/api/__init__.py
rail_django_graphql/api/serializers.py
rail_django_graphql/api/urls.py
rail_django_graphql/api/views.py
rail_django_graphql/core/__init__.py
rail_django_graphql/core/config_loader.py
rail_django_graphql/core/debug.py
rail_django_graphql/core/error_handling.py
rail_django_graphql/core/exceptions.py
rail_django_graphql/core/feature_flags.py
rail_django_graphql/core/meta.py
rail_django_graphql/core/middleware.py
rail_django_graphql/core/performance.py
rail_django_graphql/core/registry.py
rail_django_graphql/core/runtime_config.py
rail_django_graphql/core/scalars.py
rail_django_graphql/core/schema.py
rail_django_graphql/core/schema_versioning.py
rail_django_graphql/core/security.py
rail_django_graphql/core/settings.py
rail_django_graphql/debugging/__init__.py
rail_django_graphql/debugging/debug_hooks.py
rail_django_graphql/debugging/error_tracker.py
rail_django_graphql/debugging/performance_monitor.py
rail_django_graphql/debugging/query_analyzer.py
rail_django_graphql/extensions/__init__.py
rail_django_graphql/extensions/audit.py
rail_django_graphql/extensions/auth.py
rail_django_graphql/extensions/auth_decorators.py
rail_django_graphql/extensions/caching.py
rail_django_graphql/extensions/export-guide.md
rail_django_graphql/extensions/export_usage.py
rail_django_graphql/extensions/exporting.py
rail_django_graphql/extensions/health.py
rail_django_graphql/extensions/media.py
rail_django_graphql/extensions/metadata.py
rail_django_graphql/extensions/mfa.py
rail_django_graphql/extensions/optimization.py
rail_django_graphql/extensions/performance_metrics.py
rail_django_graphql/extensions/permissions.py
rail_django_graphql-1.1.7.dist-info/LICENSE
rail_django_graphql-1.1.7.dist-info/METADATA
rail_django_graphql-1.1.7.dist-info/WHEEL
rail_django_graphql-1.1.7.dist-info/top_level.txt
rail_django_graphql-1.1.7.dist-info/RECORD
