Metadata-Version: 2.1
Name: rail-django-graphql
Version: 1.1.7
Summary: A powerful Django library for automatic GraphQL API generation with advanced features
Home-page: https://github.com/raillogistic/rail-django-graphql
Author: Rail Logistic
Author-email: Rail Django GraphQL Contributors <contributors@rail-django-graphql.com>
Maintainer-email: Rail Django GraphQL Contributors <contributors@rail-django-graphql.com>
License: MIT
Project-URL: Homepage, https://github.com/raillogistic/rail-django-graphql
Project-URL: Documentation, https://rail-django-graphql.readthedocs.io/
Project-URL: Repository, https://github.com/raillogistic/rail-django-graphql.git
Project-URL: Bug Tracker, https://github.com/raillogistic/rail-django-graphql/issues
Project-URL: Changelog, https://github.com/raillogistic/rail-django-graphql/blob/main/CHANGELOG.md
Keywords: django,graphql,api,graphene,schema,generator,rail,automation
Classifier: Development Status :: 5 - Production/Stable
Classifier: Environment :: Web Environment
Classifier: Framework :: Django
Classifier: Framework :: Django :: 4.2
Classifier: Framework :: Django :: 5.0
Classifier: Framework :: Django :: 5.1
Classifier: Intended Audience :: Developers
Classifier: License :: OSI Approved :: MIT License
Classifier: Operating System :: OS Independent
Classifier: Programming Language :: Python
Classifier: Programming Language :: Python :: 3
Classifier: Programming Language :: Python :: 3.8
Classifier: Programming Language :: Python :: 3.9
Classifier: Programming Language :: Python :: 3.10
Classifier: Programming Language :: Python :: 3.11
Classifier: Programming Language :: Python :: 3.12
Classifier: Topic :: Internet :: WWW/HTTP
Classifier: Topic :: Internet :: WWW/HTTP :: Dynamic Content
Classifier: Topic :: Software Development :: Libraries :: Application Frameworks
Classifier: Topic :: Software Development :: Libraries :: Python Modules
Requires-Python: >=3.8
License-File: LICENSE
Requires-Dist: Django<6.0,>=4.2
Requires-Dist: graphene-django<4.0.0,>=3.0.0
Requires-Dist: graphene<4.0.0,>=3.0.0
Requires-Dist: django-filter<25.0,>=23.0
Requires-Dist: django-cors-headers<5.0.0,>=4.0.0
Provides-Extra: dev
Requires-Dist: pytest>=7.0.0; extra == "dev"
Requires-Dist: pytest-django>=4.5.0; extra == "dev"
Requires-Dist: pytest-cov>=4.0.0; extra == "dev"
Requires-Dist: pytest-xdist>=3.0.0; extra == "dev"
Requires-Dist: factory-boy>=3.2.0; extra == "dev"
Requires-Dist: tox>=4.0.0; extra == "dev"
Requires-Dist: black>=23.0.0; extra == "dev"
Requires-Dist: isort>=5.12.0; extra == "dev"
Requires-Dist: flake8>=6.0.0; extra == "dev"
Requires-Dist: flake8-docstrings>=1.7.0; extra == "dev"
Requires-Dist: flake8-import-order>=0.18.0; extra == "dev"
Requires-Dist: flake8-bugbear>=23.0.0; extra == "dev"
Requires-Dist: mypy>=1.0.0; extra == "dev"
Requires-Dist: bandit>=1.7.0; extra == "dev"
Requires-Dist: safety>=2.3.0; extra == "dev"
Requires-Dist: pre-commit>=3.0.0; extra == "dev"
Requires-Dist: sphinx>=6.0.0; extra == "dev"
Requires-Dist: sphinx-rtd-theme>=1.2.0; extra == "dev"
Requires-Dist: sphinx-autodoc-typehints>=1.20.0; extra == "dev"
Requires-Dist: ipython>=8.0.0; extra == "dev"
Requires-Dist: ipdb>=0.13.0; extra == "dev"
Provides-Extra: full
Requires-Dist: rail-django-graphql[dev,performance,postgres]; extra == "full"
Provides-Extra: performance
Requires-Dist: redis>=4.0.0; extra == "performance"
Requires-Dist: django-redis>=5.2.0; extra == "performance"
Requires-Dist: celery>=5.2.0; extra == "performance"
Provides-Extra: postgres
Requires-Dist: psycopg2-binary>=2.9.0; extra == "postgres"
